rwlock/__init__.py
rwlock/rwlock.py
rwlock/tests/__init__.py
rwlock/tests/test_rwlock.py
cy_rwlock-1.9.1.dist-info/LICENSE
cy_rwlock-1.9.1.dist-info/METADATA
cy_rwlock-1.9.1.dist-info/WHEEL
cy_rwlock-1.9.1.dist-info/top_level.txt
cy_rwlock-1.9.1.dist-info/RECORD
