Metadata-Version: 2.1
Name: cy-rwlock
Version: 1.9.1
Summary: RwLock: Reader-Writer lock
Home-page: https://github.com/cy-arduino/cy_rwlock
Author: ChihYing_Lin
Author-email: 
License: LGPL
Keywords: rwlock
Platform: UNKNOWN
Classifier: Natural Language :: English
Classifier: Programming Language :: Python :: 2.7
Classifier: Programming Language :: Python :: 3.5
Classifier: Programming Language :: Python :: 3.6
Classifier: Programming Language :: Python :: 3.7
Classifier: Programming Language :: Python :: 3.8
Classifier: Topic :: Software Development :: Libraries
